CHANGELOG
LICENSE
MANIFEST.in
README.rst
company.xml
configuration.xml
project.xml
setup.cfg
setup.py
timesheet.xml
tryton.cfg
user.xml
./__init__.py
./activity.py
./application.py
./attachment.py
./company.py
./company.xml
./configuration.py
./configuration.xml
./fabfile.py
./project.py
./project.xml
./tag.py
./task.py
./timesheet.py
./timesheet.xml
./tryton.cfg
./user.py
./user.xml
./utils.py
./website.py
./static/css/bootstrap-responsive.css
./static/css/bootstrap.css
./static/css/chosen-sprite.png
./static/css/chosen.css
./static/css/custom.css
./static/css/datepicker.css
./static/css/font-awesome.css
./static/css/fullcalendar.css
./static/css/jquery.gantt.css
./static/css/jquery.meow.css
./static/css/pygments.css
./static/font/fontawesome-webfont.eot
./static/font/fontawesome-webfont.svg
./static/font/fontawesome-webfont.ttf
./static/font/fontawesome-webfont.woff
./static/img/background.png
./static/img/grid.png
./static/img/icon_sprite.png
./static/img/loader_bg.png
./static/img/loading-clock.gif
./static/img/slider_handle.png
./static/js/bootstrap-datepicker.js
./static/js/bootstrap.js
./static/js/chosen.jquery.min.js
./static/js/fullcalendar.min.js
./static/js/highcharts.js
./static/js/jquery-1.8.1.min.js
./static/js/jquery-ui.js
./static/js/jquery.fn.gantt.js
./static/js/jquery.meow.js
./static/js/jquery.timeago.js
./static/js/jquery.validate.min.js
./static/js/map.google.js
./static/js/underscore.js
./static/js/modules/canvas-tools.js
./static/js/modules/canvas-tools.src.js
./static/js/modules/data.js
./static/js/modules/data.src.js
./static/js/modules/exporting.js
./static/js/modules/exporting.src.js
./static/ng-app/.bowerrc
./static/ng-app/.gitattributes
./static/ng-app/.gitignore
./static/ng-app/.jshintrc
./static/ng-app/background.js
./static/ng-app/bower.json
./static/ng-app/exclude.lst
./static/ng-app/gulpfile.js
./static/ng-app/karma.conf.js
./static/ng-app/manifest.json
./static/ng-app/package.json
./static/ng-app/app/index.html
trytond_nereid_project.egg-info/PKG-INFO
trytond_nereid_project.egg-info/SOURCES.txt
trytond_nereid_project.egg-info/dependency_links.txt
trytond_nereid_project.egg-info/entry_points.txt
trytond_nereid_project.egg-info/not-zip-safe
trytond_nereid_project.egg-info/requires.txt
trytond_nereid_project.egg-info/top_level.txt
